simple_ssh_client/__init__.py
simple_ssh_client/client.py
simple_ssh_client/schema.py
simple_ssh_client-1.0.0.dist-info/WHEEL
simple_ssh_client-1.0.0.dist-info/METADATA
simple_ssh_client-1.0.0.dist-info/RECORD
